LICENSE
MANIFEST.in
README.rst
requirements.txt
setup.py
python_tutum.egg-info/PKG-INFO
python_tutum.egg-info/SOURCES.txt
python_tutum.egg-info/dependency_links.txt
python_tutum.egg-info/requires.txt
python_tutum.egg-info/top_level.txt
tests/__init__.py
tests/fake_api.py
tests/test_action.py
tests/test_auth.py
tests/test_base.py
tests/test_container.py
tests/test_http.py
tests/test_image.py
tests/test_node.py
tests/test_nodecluster.py
tests/test_nodeprovider.py
tests/test_noderegion.py
tests/test_nodetype.py
tests/test_service.py
tests/test_utils.py
tutum/__init__.py
tutum/api/__init__.py
tutum/api/action.py
tutum/api/auth.py
tutum/api/base.py
tutum/api/container.py
tutum/api/events.py
tutum/api/exceptions.py
tutum/api/http.py
tutum/api/image.py
tutum/api/imagetag.py
tutum/api/node.py
tutum/api/nodeaz.py
tutum/api/nodecluster.py
tutum/api/nodeprovider.py
tutum/api/noderegion.py
tutum/api/nodetype.py
tutum/api/service.py
tutum/api/stack.py
tutum/api/tag.py
tutum/api/trigger.py
tutum/api/utils.py
tutum/api/volume.py
tutum/api/volumegroup.py