Metadata-Version: 1.1
Name: python-tutum
Version: 0.16.21
Summary: Python Library for Tutum
Home-page: http://www.tutum.co/
Author: Tutum, Inc.
Author-email: info@tutum.co
License: Apache v2
Keywords: tutum docker
Platform: UNKNOWN
Provides: tutum
